chz/__init__.py
chz/data_model.py
chz/factories.py
chz/field.py
chz/mungers.py
chz/py.typed
chz/tiepin.py
chz/util.py
chz/validators.py
chz/blueprint/__init__.py
chz/blueprint/_argmap.py
chz/blueprint/_argv.py
chz/blueprint/_blueprint.py
chz/blueprint/_entrypoint.py
chz/blueprint/_lazy.py
chz/blueprint/_wildcard.py
chz-0.3.0.dist-info/LICENSE
chz-0.3.0.dist-info/METADATA
chz-0.3.0.dist-info/WHEEL
chz-0.3.0.dist-info/top_level.txt
chz-0.3.0.dist-info/RECORD
