Metadata-Version: 2.2
Name: chz
Version: 0.3.0
Summary: chz is a library for managing configuration
Author: Shantanu Jain
Author-email: shantanu@openai.com
License: MIT License
Project-URL: homepage, https://github.com/openai/chz
Project-URL: repository, https://github.com/openai/chz
Project-URL: changelog, https://github.com/openai/chz/blob/main/CHANGELOG.md
Requires-Python: >=3.11
License-File: LICENSE
Requires-Dist: typing-extensions>=4.7
